uci/__init__.py
uci/datasets.py
uci/helpers.py
ucimlr/__init__.py
ucimlr/classification_datasets.py
ucimlr/constants.py
ucimlr/dataset.py
ucimlr/datasets.py
ucimlr/helpers.py
ucimlr/regression_datasets.py
ucimlr-0.3.0.dist-info/LICENSE
ucimlr-0.3.0.dist-info/METADATA
ucimlr-0.3.0.dist-info/WHEEL
ucimlr-0.3.0.dist-info/top_level.txt
ucimlr-0.3.0.dist-info/RECORD
