Metadata-Version: 2.1
Name: ucimlr
Version: 0.3.0
Summary: Easy access to datasets from the UCI Machine Learning Repository
Home-page: https://github.com/isacarnekvist/ucimlr
Author: Isac Arnekvist
Author-email: isac.arnekvist@gmail.com
License: UNKNOWN
Platform: UNKNOWN
Requires-Python: >=3.6
Requires-Dist: numpy (>=1.18.2)
Requires-Dist: pandas (>=1.0.3)
Requires-Dist: sklearn (>=0.0)
Requires-Dist: unlzw (>=0.1.1)
Requires-Dist: xlrd (>=1.0.0)
